audio_seek/__init__.py
audio_seek/_audio_seek.py
audio_seek/ensure_mono.py
audio_seek/read_audio_segment.py
audio_seek-0.1.0.dist-info/METADATA
audio_seek-0.1.0.dist-info/WHEEL
audio_seek-0.1.0.dist-info/licenses/LICENSE
audio_seek-0.1.0.dist-info/RECORD
