Metadata-Version: 2.4
Name: audio-seek
Version: 0.1.0
Summary: Efficient audio seeking library with O(1) complexity. Automatically selects best seekable compression format for maximum compatibility.
License: MIT
License-File: LICENSE
Author: Allen Chou
Author-email: f1470891079@gmail.com
Requires-Python: >=3.11,<4
Classifier: License :: OSI Approved :: MIT License
Classifier: Programming Language :: Python :: 3
Classifier: Programming Language :: Python :: 3.11
Classifier: Programming Language :: Python :: 3.12
Classifier: Programming Language :: Python :: 3.13
Classifier: Programming Language :: Python :: 3.14
Requires-Dist: librosa
Requires-Dist: llvmlite (>=0.43.0,<1.0.0)
Requires-Dist: numba (>=0.60.0,<1.0.0)
Requires-Dist: numpy
Requires-Dist: soundfile
Project-URL: Homepage, https://github.com/allen2c/audio-seek
Project-URL: PyPI, https://pypi.org/project/audio-seek/
Project-URL: Repository, https://github.com/allen2c/audio-seek
